README.md
setup.py
synchrolog_django/__init__.py
synchrolog_django/logging.py
synchrolog_django/middleware.py
synchrolog_django/threadlocal.py
synchrolog_django.egg-info/PKG-INFO
synchrolog_django.egg-info/SOURCES.txt
synchrolog_django.egg-info/dependency_links.txt
synchrolog_django.egg-info/requires.txt
synchrolog_django.egg-info/top_level.txt