Metadata-Version: 1.0
Name: synchrolog-django
Version: 0.0.1
Summary: Django middleware that sends request logs to Synchrolog
Home-page: https://github.com/synchrolog/synchrolog-django
Author: Synchrolog
Author-email: hello@synchrolog.com
License: Apache-2.0
Platform: UNKNOWN
